pya/__init__.py
pya/amfcc.py
pya/arecorder.py
pya/aserver.py
pya/asig.py
pya/aspec.py
pya/astft.py
pya/ugen.py
pya/version.py
pya/backend/Dummy.py
pya/backend/Jupyter.py
pya/backend/PyAudio.py
pya/backend/__init__.py
pya/backend/base.py
pya/helper/__init__.py
pya/helper/backend.py
pya/helper/codec.py
pya/helper/helpers.py
pya/helper/visualization.py
pya-0.5.2.dist-info/LICENSE
pya-0.5.2.dist-info/METADATA
pya-0.5.2.dist-info/WHEEL
pya-0.5.2.dist-info/top_level.txt
pya-0.5.2.dist-info/RECORD
