Metadata-Version: 2.1
Name: pya
Version: 0.5.2
Summary: Python audio coding classes - for dsp and sonification
Home-page: https://github.com/interactive-sonification/pya
Author: Thomas Hermann
Author-email: thermann@techfak.uni-bielefeld.de
License: MIT
Keywords: sonification, sound synthesis
Classifier: Programming Language :: Python :: 3
Classifier: Development Status :: 4 - Beta
Classifier: License :: OSI Approved :: MIT License
Classifier: Operating System :: OS Independent
Classifier: Topic :: Multimedia :: Sound/Audio
Classifier: Topic :: Multimedia :: Sound/Audio :: Analysis
Classifier: Topic :: Multimedia :: Sound/Audio :: Sound Synthesis
License-File: LICENSE
Requires-Dist: pyamapping
Requires-Dist: scipy>=1.7.3
Requires-Dist: matplotlib>=3.5.3
Provides-Extra: remote
Requires-Dist: notebook; extra == "remote"
Requires-Dist: websockets; extra == "remote"
Requires-Dist: ipywidgets; extra == "remote"
Provides-Extra: pyaudio
Requires-Dist: pyaudio>=0.2.12; python_version >= "3.10" and extra == "pyaudio"
Requires-Dist: pyaudio>=0.2.11; python_version < "3.10" and extra == "pyaudio"
